blockscope/__init__.py
blockscope/scope.py
360blockscope-0.1.0.dist-info/LICENSE
360blockscope-0.1.0.dist-info/METADATA
360blockscope-0.1.0.dist-info/WHEEL
360blockscope-0.1.0.dist-info/RECORD
