Metadata-Version: 2.1
Name: 360blockscope
Version: 0.1.0
Summary: Block scoping for python
License: MIT
Author: Davis Yoshida
Author-email: dyoshida@ttic.edu
Requires-Python: >=3.9,<4.0
Classifier: License :: OSI Approved :: MIT License
Classifier: Programming Language :: Python :: 3
Classifier: Programming Language :: Python :: 3.9
Classifier: Programming Language :: Python :: 3.10
Classifier: Programming Language :: Python :: 3.11
